samppl/__init__.py
samppl-0.0.0.dist-info/LICENSE
samppl-0.0.0.dist-info/METADATA
samppl-0.0.0.dist-info/WHEEL
samppl-0.0.0.dist-info/top_level.txt
samppl-0.0.0.dist-info/RECORD
